[{"teacher id":1,"teachers name":"Trevor Barker","teachers salary":1},{"teacher id":2,"teachers name":"Robyn Cox DDS","teachers salary":2},{"teacher id":3,"teachers name":"Cody Sanders","teachers salary":3},{"teacher id":4,"teachers name":"Christine Haas","teachers salary":4},{"teacher id":5,"teachers name":"Brent Smith","teachers salary":5},{"teacher id":6,"teachers name":"Steven Hale","teachers salary":6},{"teacher id":7,"teachers name":"Mr. Matthew Faulkner","teachers salary":7},{"teacher id":8,"teachers name":"Ashley Lewis","teachers salary":8},{"teacher id":9,"teachers name":"John Jones","teachers salary":9},{"teacher id":10,"teachers name":"Joshua Fowler","teachers salary":10},{"teacher id":11,"teachers name":"April Bryant","teachers salary":11},{"teacher id":12,"teachers name":"Brittany Norris","teachers salary":12},{"teacher id":13,"teachers name":"Mike Scott","teachers salary":13},{"teacher id":14,"teachers name":"Jamie Stone","teachers salary":14},{"teacher id":15,"teachers name":"Wayne Smith","teachers salary":15},{"teacher id":16,"teachers name":"Aaron Marshall","teachers salary":16},{"teacher id":17,"teachers name":"Mark Shaw","teachers salary":17},{"teacher id":18,"teachers name":"Daniel Spencer","teachers salary":18},{"teacher id":19,"teachers name":"Jessica Marshall","teachers salary":19},{"teacher id":20,"teachers name":"Mary Anderson","teachers salary":20},{"teacher id":21,"teachers name":"Emily Monroe","teachers salary":21},{"teacher id":22,"teachers name":"Denise Jones","teachers salary":22},{"teacher id":23,"teachers name":"Kayla Hickman","teachers salary":23},{"teacher id":24,"teachers name":"Allen Macias","teachers salary":24},{"teacher id":25,"teachers name":"Mr. Johnathan Pratt","teachers salary":25},{"teacher id":26,"teachers name":"Jacob Tucker","teachers salary":26},{"teacher id":27,"teachers name":"Kayla Brooks","teachers salary":27},{"teacher id":28,"teachers name":"John Torres","teachers salary":28},{"teacher id":29,"teachers name":"Jeremy Harris","teachers salary":29},{"teacher id":30,"teachers name":"Rachel Lopez","teachers salary":30},{"teacher id":31,"teachers name":"Joseph Robles","teachers salary":31},{"teacher id":32,"teachers name":"Nicole Dominguez","teachers salary":32},{"teacher id":33,"teachers name":"Mikayla Gregory","teachers salary":33},{"teacher id":34,"teachers name":"Sean Johnson","teachers salary":34},{"teacher id":35,"teachers name":"Theodore Waters","teachers salary":35},{"teacher id":36,"teachers name":"Pamela Warren","teachers salary":36},{"teacher id":37,"teachers name":"Mark Powell","teachers salary":37},{"teacher id":38,"teachers name":"Allison Garcia","teachers salary":38},{"teacher id":39,"teachers name":"Sherry Martinez","teachers salary":39},{"teacher id":40,"teachers name":"Jeremy Jackson","teachers salary":40},{"teacher id":41,"teachers name":"Brian Yoder","teachers salary":41},{"teacher id":42,"teachers name":"Mr. John Farmer","teachers salary":42},{"teacher id":43,"teachers name":"Amanda Williams","teachers salary":43},{"teacher id":44,"teachers name":"Christopher Obrien","teachers salary":44},{"teacher id":45,"teachers name":"Julie Savage","teachers salary":45},{"teacher id":46,"teachers name":"Carmen Harper","teachers salary":46},{"teacher id":47,"teachers name":"Jo Finley","teachers salary":47},{"teacher id":48,"teachers name":"Amy Holmes","teachers salary":48},{"teacher id":49,"teachers name":"Carl Mitchell","teachers salary":49},{"teacher id":50,"teachers name":"Elizabeth Hill","teachers salary":50}]